lebrydb/__init__.py
lebrydb/lebrydb.log
lebrydb/lebrydb.py
lebrydb-0.1.6.dist-info/METADATA
lebrydb-0.1.6.dist-info/WHEEL
lebrydb-0.1.6.dist-info/RECORD
