Metadata-Version: 2.1
Name: lebrydb
Version: 0.1.6
Summary:  LebryDB é uma biblioteca Python que oferece uma solução simples para gerenciar dados NoSQL em formato JSON. Com ela, você pode criar e gerenciar uma base de dados NoSQL em seu aplicativo Python sem a necessidade de um sistema de gerenciamento de banco de dados completo. A classe permite a inserção, atualização, exclusão e consulta de documentos, tornando-a ideal para projetos que não exigem complexidade excessiva de um banco de dados tradicional.
Author: Bruno Ragner
Author-email: brunooragnner@gmail.com
Requires-Python: >=3.11,<4.0
Classifier: Programming Language :: Python :: 3
Classifier: Programming Language :: Python :: 3.11
